Workbook

Sheet Instructions
A1: Personal Management 13-Week Tracking Workbook
A3: Purpose | B3: Use this workbook to plan a budget, track real income and expenses for 13 consecutive weeks, compare budget vs. actual, and prepare for your final counselor discussion.
A4: Official requirements | B4: Use the current official merit badge pamphlet and official requirements as the source of truth. This workbook supports the process but does not replace the requirements.
A5: How to use | B5: 1) Fill in the Timeline sheet. 2) Draft a weekly budget on Budget Plan. 3) Enter each real transaction on Transaction Log. 4) Review Weekly Summary. 5) Complete Major Purchase Plan and Final Reflection.
A6: Counselor expectation | B6: Track real money as it happens. Do not backfill the full 13 weeks from memory.

Sheet Timeline
A1: Scout and Timeline
A3: Scout name
A4: Kickoff date
A5: 13-week start date
A6: Target final review date | B6: =IF(B4="","",B4+91)
A7: Counselor
A8: Tracking method | B8: Spreadsheet / app / notebook
A10: Week | B10: Start Date | C10: End Date
A11: 1 | B11: =IF($B$4="","",$B$4+((1-1)*7)) | C11: =IF(B11="","",B11+6)
A12: 2 | B12: =IF($B$4="","",$B$4+((2-1)*7)) | C12: =IF(B12="","",B12+6)
A13: 3 | B13: =IF($B$4="","",$B$4+((3-1)*7)) | C13: =IF(B13="","",B13+6)
A14: 4 | B14: =IF($B$4="","",$B$4+((4-1)*7)) | C14: =IF(B14="","",B14+6)
A15: 5 | B15: =IF($B$4="","",$B$4+((5-1)*7)) | C15: =IF(B15="","",B15+6)
A16: 6 | B16: =IF($B$4="","",$B$4+((6-1)*7)) | C16: =IF(B16="","",B16+6)
A17: 7 | B17: =IF($B$4="","",$B$4+((7-1)*7)) | C17: =IF(B17="","",B17+6)
A18: 8 | B18: =IF($B$4="","",$B$4+((8-1)*7)) | C18: =IF(B18="","",B18+6)
A19: 9 | B19: =IF($B$4="","",$B$4+((9-1)*7)) | C19: =IF(B19="","",B19+6)
A20: 10 | B20: =IF($B$4="","",$B$4+((10-1)*7)) | C20: =IF(B20="","",B20+6)
A21: 11 | B21: =IF($B$4="","",$B$4+((11-1)*7)) | C21: =IF(B21="","",B21+6)
A22: 12 | B22: =IF($B$4="","",$B$4+((12-1)*7)) | C22: =IF(B22="","",B22+6)
A23: 13 | B23: =IF($B$4="","",$B$4+((13-1)*7)) | C23: =IF(B23="","",B23+6)

Sheet Budget Plan
A1: Weekly Budget Plan
A3: Type | B3: Category | C3: Weekly Planned Amount | D3: Notes | E3: 13-Week Planned Total
A4: Income | B4: Allowance | C4: 0 | E4: =C4*13 -> 0
A5: Income | B5: Job/Gig | C5: 0 | E5: =C5*13 -> 0
A6: Income | B6: Gifts | C6: 0 | E6: =C6*13 -> 0
A7: Income | B7: Other Income | C7: 0 | E7: =C7*13 -> 0
A8: Expense | B8: Food/Snacks | C8: 0 | E8: =C8*13 -> 0
A9: Expense | B9: Entertainment | C9: 0 | E9: =C9*13 -> 0
A10: Expense | B10: Gear/Clothing | C10: 0 | E10: =C10*13 -> 0
A11: Expense | B11: Transportation | C11: 0 | E11: =C11*13 -> 0
A12: Expense | B12: Giving | C12: 0 | E12: =C12*13 -> 0
A13: Expense | B13: Savings | C13: 0 | E13: =C13*13 -> 0
A14: Expense | B14: Other Expense | C14: 0 | E14: =C14*13 -> 0

Sheet Transaction Log
A1: Transaction Log
A3: Date | B3: Week # | C3: Type | D3: Category | E3: Description | F3: Amount | G3: Payment Method | H3: Need/Want | I3: Notes
B4: =IF(OR(A4="",Timeline!$B$4=""),"",MIN(13,MAX(1,INT((A4-Timeline!$B$4)/7)+1)))
B5: =IF(OR(A5="",Timeline!$B$4=""),"",MIN(13,MAX(1,INT((A5-Timeline!$B$4)/7)+1)))
B6: =IF(OR(A6="",Timeline!$B$4=""),"",MIN(13,MAX(1,INT((A6-Timeline!$B$4)/7)+1)))
B7: =IF(OR(A7="",Timeline!$B$4=""),"",MIN(13,MAX(1,INT((A7-Timeline!$B$4)/7)+1)))
B8: =IF(OR(A8="",Timeline!$B$4=""),"",MIN(13,MAX(1,INT((A8-Timeline!$B$4)/7)+1)))
B9: =IF(OR(A9="",Timeline!$B$4=""),"",MIN(13,MAX(1,INT((A9-Timeline!$B$4)/7)+1)))
B10: =IF(OR(A10="",Timeline!$B$4=""),"",MIN(13,MAX(1,INT((A10-Timeline!$B$4)/7)+1)))
B11: =IF(OR(A11="",Timeline!$B$4=""),"",MIN(13,MAX(1,INT((A11-Timeline!$B$4)/7)+1)))
B12: =IF(OR(A12="",Timeline!$B$4=""),"",MIN(13,MAX(1,INT((A12-Timeline!$B$4)/7)+1)))
B13: =IF(OR(A13="",Timeline!$B$4=""),"",MIN(13,MAX(1,INT((A13-Timeline!$B$4)/7)+1)))
B14: =IF(OR(A14="",Timeline!$B$4=""),"",MIN(13,MAX(1,INT((A14-Timeline!$B$4)/7)+1)))
B15: =IF(OR(A15="",Timeline!$B$4=""),"",MIN(13,MAX(1,INT((A15-Timeline!$B$4)/7)+1)))
... B203: =IF(OR(A203="",Timeline!$B$4=""),"",MIN(13,MAX(1,INT((A203-Timeline!$B$4)/7)+1)))

Sheet Weekly Summary
A1: Budget vs. Actual Weekly Summary
A3: Week | B3: Planned Income | C3: Actual Income | D3: Income Variance | E3: Planned Expenses | F3: Actual Expenses | G3: Expense Variance | H3: Actual Net | I3: Notes
A4: 1 | B4: =SUMIFS('Budget Plan'!$E:$E,'Budget Plan'!$A:$A,"Income") -> 0 | C4: =SUMIFS('Transaction Log'!$F:$F,'Transaction Log'!$C:$C,"Income",'Transaction Log'!$B:$B,A4) -> 0 | D4: =C4-B4 -> 0 | E4: =SUMIFS('Budget Plan'!$E:$E,'Budget Plan'!$A:$A,"Expense") -> 0 | F4: =SUMIFS('Transaction Log'!$F:$F,'Transaction Log'!$C:$C,"Expense",'Transaction Log'!$B:$B,A4) -> 0 | G4: =F4-E4 -> 0 | H4: =C4-F4 -> 0
A5: 2 | B5: =SUMIFS('Budget Plan'!$E:$E,'Budget Plan'!$A:$A,"Income") -> 0 | C5: =SUMIFS('Transaction Log'!$F:$F,'Transaction Log'!$C:$C,"Income",'Transaction Log'!$B:$B,A5) -> 0 | D5: =C5-B5 -> 0 | E5: =SUMIFS('Budget Plan'!$E:$E,'Budget Plan'!$A:$A,"Expense") -> 0 | F5: =SUMIFS('Transaction Log'!$F:$F,'Transaction Log'!$C:$C,"Expense",'Transaction Log'!$B:$B,A5) -> 0 | G5: =F5-E5 -> 0 | H5: =C5-F5 -> 0
A6: 3 | B6: =SUMIFS('Budget Plan'!$E:$E,'Budget Plan'!$A:$A,"Income") -> 0 | C6: =SUMIFS('Transaction Log'!$F:$F,'Transaction Log'!$C:$C,"Income",'Transaction Log'!$B:$B,A6) -> 0 | D6: =C6-B6 -> 0 | E6: =SUMIFS('Budget Plan'!$E:$E,'Budget Plan'!$A:$A,"Expense") -> 0 | F6: =SUMIFS('Transaction Log'!$F:$F,'Transaction Log'!$C:$C,"Expense",'Transaction Log'!$B:$B,A6) -> 0 | G6: =F6-E6 -> 0 | H6: =C6-F6 -> 0
A7: 4 | B7: =SUMIFS('Budget Plan'!$E:$E,'Budget Plan'!$A:$A,"Income") -> 0 | C7: =SUMIFS('Transaction Log'!$F:$F,'Transaction Log'!$C:$C,"Income",'Transaction Log'!$B:$B,A7) -> 0 | D7: =C7-B7 -> 0 | E7: =SUMIFS('Budget Plan'!$E:$E,'Budget Plan'!$A:$A,"Expense") -> 0 | F7: =SUMIFS('Transaction Log'!$F:$F,'Transaction Log'!$C:$C,"Expense",'Transaction Log'!$B:$B,A7) -> 0 | G7: =F7-E7 -> 0 | H7: =C7-F7 -> 0
A8: 5 | B8: =SUMIFS('Budget Plan'!$E:$E,'Budget Plan'!$A:$A,"Income") -> 0 | C8: =SUMIFS('Transaction Log'!$F:$F,'Transaction Log'!$C:$C,"Income",'Transaction Log'!$B:$B,A8) -> 0 | D8: =C8-B8 -> 0 | E8: =SUMIFS('Budget Plan'!$E:$E,'Budget Plan'!$A:$A,"Expense") -> 0 | F8: =SUMIFS('Transaction Log'!$F:$F,'Transaction Log'!$C:$C,"Expense",'Transaction Log'!$B:$B,A8) -> 0 | G8: =F8-E8 -> 0 | H8: =C8-F8 -> 0
A9: 6 | B9: =SUMIFS('Budget Plan'!$E:$E,'Budget Plan'!$A:$A,"Income") -> 0 | C9: =SUMIFS('Transaction Log'!$F:$F,'Transaction Log'!$C:$C,"Income",'Transaction Log'!$B:$B,A9) -> 0 | D9: =C9-B9 -> 0 | E9: =SUMIFS('Budget Plan'!$E:$E,'Budget Plan'!$A:$A,"Expense") -> 0 | F9: =SUMIFS('Transaction Log'!$F:$F,'Transaction Log'!$C:$C,"Expense",'Transaction Log'!$B:$B,A9) -> 0 | G9: =F9-E9 -> 0 | H9: =C9-F9 -> 0
A10: 7 | B10: =SUMIFS('Budget Plan'!$E:$E,'Budget Plan'!$A:$A,"Income") -> 0 | C10: =SUMIFS('Transaction Log'!$F:$F,'Transaction Log'!$C:$C,"Income",'Transaction Log'!$B:$B,A10) -> 0 | D10: =C10-B10 -> 0 | E10: =SUMIFS('Budget Plan'!$E:$E,'Budget Plan'!$A:$A,"Expense") -> 0 | F10: =SUMIFS('Transaction Log'!$F:$F,'Transaction Log'!$C:$C,"Expense",'Transaction Log'!$B:$B,A10) -> 0 | G10: =F10-E10 -> 0 | H10: =C10-F10 -> 0
A11: 8 | B11: =SUMIFS('Budget Plan'!$E:$E,'Budget Plan'!$A:$A,"Income") -> 0 | C11: =SUMIFS('Transaction Log'!$F:$F,'Transaction Log'!$C:$C,"Income",'Transaction Log'!$B:$B,A11) -> 0 | D11: =C11-B11 -> 0 | E11: =SUMIFS('Budget Plan'!$E:$E,'Budget Plan'!$A:$A,"Expense") -> 0 | F11: =SUMIFS('Transaction Log'!$F:$F,'Transaction Log'!$C:$C,"Expense",'Transaction Log'!$B:$B,A11) -> 0 | G11: =F11-E11 -> 0 | H11: =C11-F11 -> 0
A12: 9 | B12: =SUMIFS('Budget Plan'!$E:$E,'Budget Plan'!$A:$A,"Income") -> 0 | C12: =SUMIFS('Transaction Log'!$F:$F,'Transaction Log'!$C:$C,"Income",'Transaction Log'!$B:$B,A12) -> 0 | D12: =C12-B12 -> 0 | E12: =SUMIFS('Budget Plan'!$E:$E,'Budget Plan'!$A:$A,"Expense") -> 0 | F12: =SUMIFS('Transaction Log'!$F:$F,'Transaction Log'!$C:$C,"Expense",'Transaction Log'!$B:$B,A12) -> 0 | G12: =F12-E12 -> 0 | H12: =C12-F12 -> 0
A13: 10 | B13: =SUMIFS('Budget Plan'!$E:$E,'Budget Plan'!$A:$A,"Income") -> 0 | C13: =SUMIFS('Transaction Log'!$F:$F,'Transaction Log'!$C:$C,"Income",'Transaction Log'!$B:$B,A13) -> 0 | D13: =C13-B13 -> 0 | E13: =SUMIFS('Budget Plan'!$E:$E,'Budget Plan'!$A:$A,"Expense") -> 0 | F13: =SUMIFS('Transaction Log'!$F:$F,'Transaction Log'!$C:$C,"Expense",'Transaction Log'!$B:$B,A13) -> 0 | G13: =F13-E13 -> 0 | H13: =C13-F13 -> 0
A14: 11 | B14: =SUMIFS('Budget Plan'!$E:$E,'Budget Plan'!$A:$A,"Income") -> 0 | C14: =SUMIFS('Transaction Log'!$F:$F,'Transaction Log'!$C:$C,"Income",'Transaction Log'!$B:$B,A14) -> 0 | D14: =C14-B14 -> 0 | E14: =SUMIFS('Budget Plan'!$E:$E,'Budget Plan'!$A:$A,"Expense") -> 0 | F14: =SUMIFS('Transaction Log'!$F:$F,'Transaction Log'!$C:$C,"Expense",'Transaction Log'!$B:$B,A14) -> 0 | G14: =F14-E14 -> 0 | H14: =C14-F14 -> 0
A15: 12 | B15: =SUMIFS('Budget Plan'!$E:$E,'Budget Plan'!$A:$A,"Income") -> 0 | C15: =SUMIFS('Transaction Log'!$F:$F,'Transaction Log'!$C:$C,"Income",'Transaction Log'!$B:$B,A15) -> 0 | D15: =C15-B15 -> 0 | E15: =SUMIFS('Budget Plan'!$E:$E,'Budget Plan'!$A:$A,"Expense") -> 0 | F15: =SUMIFS('Transaction Log'!$F:$F,'Transaction Log'!$C:$C,"Expense",'Transaction Log'!$B:$B,A15) -> 0 | G15: =F15-E15 -> 0 | H15: =C15-F15 -> 0
A16: 13 | B16: =SUMIFS('Budget Plan'!$E:$E,'Budget Plan'!$A:$A,"Income") -> 0 | C16: =SUMIFS('Transaction Log'!$F:$F,'Transaction Log'!$C:$C,"Income",'Transaction Log'!$B:$B,A16) -> 0 | D16: =C16-B16 -> 0 | E16: =SUMIFS('Budget Plan'!$E:$E,'Budget Plan'!$A:$A,"Expense") -> 0 | F16: =SUMIFS('Transaction Log'!$F:$F,'Transaction Log'!$C:$C,"Expense",'Transaction Log'!$B:$B,A16) -> 0 | G16: =F16-E16 -> 0 | H16: =C16-F16 -> 0
A18: 13-Week Total | B18: =SUM(B4:B16) -> 0 | C18: =SUM(C4:C16) -> 0 | D18: =SUM(D4:D16) -> 0 | E18: =SUM(E4:E16) -> 0 | F18: =SUM(F4:F16) -> 0 | G18: =SUM(G4:G16) -> 0 | H18: =SUM(H4:H16) -> 0

Sheet Major Purchase Plan
A1: Major Purchase and Savings Plan
A3: Item or goal
A4: Why it matters
A5: Target purchase date
A6: Chosen option cost | B6: 0
A7: Money already saved | B7: 0
A8: Weekly savings target | B8: 0
A9: Weeks needed | B9: =IF(B8<=0,"",ROUNDUP(MAX(B6-B7,0)/B8,0))
A10: Tradeoffs I will make
A13: Option | B13: Vendor/Source | C13: Price | D13: Pros | E13: Cons | F13: Need/Want | G13: Decision Notes

Sheet Final Reflection
A1: Final Reflection and Counselor Discussion Prep
A3: Prompt | B3: Scout notes
A4: Where did your original budget plan break or change?
A5: Which spending category surprised you most?
A6: What would you change if you restarted the 13-week period?
A7: What did you learn about saving for a major purchase?
A8: How did tracking affect your choices?
A9: What money-management habit do you want to keep?
A10: What questions do you still have for your counselor?
